ezcx/__init__.py
ezcx/cli.py
ezcx/server/__init__.py
ezcx/server/server.py
ezcx/webhooks/__init__.py
ezcx/webhooks/request.py
ezcx/webhooks/response.py
ezcx/webhooks/rich_content.py
ezcx-0.2.3.dist-info/LICENSE
ezcx-0.2.3.dist-info/METADATA
ezcx-0.2.3.dist-info/WHEEL
ezcx-0.2.3.dist-info/entry_points.txt
ezcx-0.2.3.dist-info/top_level.txt
ezcx-0.2.3.dist-info/RECORD
